applyaf/__init__.py
applyaf/applyaf.py
applyaf-2.1.1.dist-info/METADATA
applyaf-2.1.1.dist-info/WHEEL
applyaf-2.1.1.dist-info/licenses/AUTHORS.md
applyaf-2.1.1.dist-info/licenses/LICENSE.txt
applyaf-2.1.1.dist-info/RECORD
