Metadata-Version: 2.4
Name: applyaf
Version: 2.1.1
Summary: Apply antenna factors and cable loss to spectrum analyzer measurements
Project-URL: Homepage, https://github.com/questrail/applyaf
Project-URL: Issues, https://github.com/questrail/applyaf/issues
Author-email: Matthew Rankin <matthew@questrail.com>
License-File: AUTHORS.md
License-File: LICENSE.txt
Classifier: Development Status :: 5 - Production/Stable
Classifier: Intended Audience :: Developers
Classifier: License :: OSI Approved :: MIT License
Classifier: Operating System :: OS Independent
Classifier: Programming Language :: Python
Classifier: Programming Language :: Python :: 3
Classifier: Programming Language :: Python :: 3.12
Classifier: Programming Language :: Python :: 3.13
Classifier: Topic :: Software Development :: Libraries :: Python Modules
Requires-Python: >=3.12
Requires-Dist: numpy>=2.2.0
